{
    "msg": "ok",
    "status": 0,
    "data": {
        "movieList": [{
                "id": 341139,
                "haspromotionTag": false,
                "img": "https://p0.meituan.net/w.h/movie/034069fc367db8a7d9644717b416cc2c332883.jpg",
                "version": "v3d imax",
                "nm": "惊奇队长",
                "preShow": false,
                "sc": 0,
                "gobalReleased": false,
                "wish": 426078,
                "star": "布丽 · 拉尔森,塞缪尔 · 杰克逊,本 · 门德尔森",
                "rt": "2019-03-08",
                "showInfo": "今天251家影院放映334场",
                "showst": 4,
                "wishst": 0
            },
            {
                "id": 1206605,
                "haspromotionTag": false,
                "img": "https://p1.meituan.net/w.h/movie/c9b280de01549fcb71913edec05880585769972.jpg",
                "version": "",
                "nm": "绿皮书",
                "preShow": false,
                "sc": 9.6,
                "gobalReleased": true,
                "wish": 40834,
                "star": "维果 · 莫腾森,马赫沙拉 · 阿里,琳达 · 卡德里尼",
                "rt": "2019-03-01",
                "showInfo": "今天307家影院放映3157场",
                "showst": 3,
                "wishst": 0
            },
            {
                "id": 7000000,
                "haspromotionTag": false,
                "img": "https://p0.meituan.net/w.h/movie/034069fc367db8a7d9644717b416cc2c332883.jpg",
                "version": "v3d imax",
                "nm": "惊奇队长[test]",
                "preShow": false,
                "sc": 0,
                "gobalReleased": false,
                "wish": 426078,
                "star": "布丽 · 拉尔森,塞缪尔 · 杰克逊,本 · 门德尔森",
                "rt": "2019-03-08",
                "showInfo": "今天251家影院放映334场",
                "showst": 4,
                "wishst": 0
            },
            {
                "id": 7000001,
                "haspromotionTag": false,
                "img": "https://p1.meituan.net/w.h/movie/c9b280de01549fcb71913edec05880585769972.jpg",
                "version": "",
                "nm": "绿皮书[test]",
                "preShow": false,
                "sc": 9.6,
                "gobalReleased": true,
                "wish": 40834,
                "star": "维果 · 莫腾森,马赫沙拉 · 阿里,琳达 · 卡德里尼",
                "rt": "2019-03-01",
                "showInfo": "今天307家影院放映3157场",
                "showst": 3,
                "wishst": 0
            },
            {
                "id": 7000003,
                "haspromotionTag": false,
                "img": "https://p0.meituan.net/w.h/movie/034069fc367db8a7d9644717b416cc2c332883.jpg",
                "version": "v3d imax",
                "nm": "惊奇队长[test]",
                "preShow": false,
                "sc": 0,
                "gobalReleased": false,
                "wish": 426078,
                "star": "布丽 · 拉尔森,塞缪尔 · 杰克逊,本 · 门德尔森",
                "rt": "2019-03-08",
                "showInfo": "今天251家影院放映334场",
                "showst": 4,
                "wishst": 0
            },
            {
                "id": 7000004,
                "haspromotionTag": false,
                "img": "https://p1.meituan.net/w.h/movie/c9b280de01549fcb71913edec05880585769972.jpg",
                "version": "",
                "nm": "绿皮书[test]",
                "preShow": false,
                "sc": 9.6,
                "gobalReleased": true,
                "wish": 40834,
                "star": "维果 · 莫腾森,马赫沙拉 · 阿里,琳达 · 卡德里尼",
                "rt": "2019-03-01",
                "showInfo": "今天307家影院放映3157场",
                "showst": 3,
                "wishst": 0
            }
        ]
    }
}